partest/__init__.py
partest/allure_graph.py
partest/call_storage.py
partest/client.py
partest/coverage.py
partest/methods.py
partest/parparser.py
partest/test_types.py
partest/zorro_report.py
partest/utils/__init__.py
partest/utils/ascii.py
partest/utils/checking.py
partest/utils/compare_stands.py
partest/utils/date.py
partest/utils/headers.py
partest/utils/headers_manager.py
partest/utils/logger.py
partest/utils/params_manager.py
partest/utils/response_timer.py
partest-0.2.19.dist-info/METADATA
partest-0.2.19.dist-info/WHEEL
partest-0.2.19.dist-info/top_level.txt
partest-0.2.19.dist-info/RECORD
