Metadata-Version: 2.4
Name: partest
Version: 0.2.19
Summary: This is a module for the rapid implementation of test cases with coverage tracking. This module contains a call counter for specific endpoints and their methods. As well as the function of determining the types of tests that need to be counted.
Home-page: https://github.com/Dec01/partest
Author: dec01
Author-email: parschin.ewg@yandex.ru
Project-URL: Source, https://github.com/Dec01/partest
Keywords: autotest partest test coverage
Classifier: Programming Language :: Python :: 3.8
Classifier: Programming Language :: Python :: 3.9
Classifier: Programming Language :: Python :: 3.10
Classifier: License :: OSI Approved :: MIT License
Classifier: Operating System :: OS Independent
Requires-Python: >=3.8
Requires-Dist: httpx>=0.27.2
Requires-Dist: pyyaml>=6.0.2
Requires-Dist: matplotlib>=3.9.2
Requires-Dist: allure-pytest>=2.8.18
Requires-Dist: pytest-asyncio>=0.23.7
Requires-Dist: pytest==8.3.3
Dynamic: author
Dynamic: author-email
Dynamic: classifier
Dynamic: description
Dynamic: description-content-type
Dynamic: home-page
Dynamic: keywords
Dynamic: project-url
Dynamic: requires-dist
Dynamic: requires-python
Dynamic: summary
